{"error":"Payment required","x402":{"x402Version":1,"error":"Payment required","accepts":[{"scheme":"exact","network":"xlayer-mainnet","maxAmountRequired":"10000","resource":"http://lucarne-polybot-production.up.railway.app/intel/FRA","description":"LUCARNE Signal Intel Brief — France (WC 2026)","mimeType":"application/json","payTo":"0x2Dcbd50173bB570BB5257223bfDb6b92520FAe81","maxTimeoutSeconds":300,"asset":"0x74b7f16337b8972027f6196a17a631ac6de26d22","extra":{"name":"USD Coin","version":"2"}}]}}